{

    "filters": [
          {
              "name": "SimTimeFromDatTime",
              "function": "SimTimeFromDatTime"
          },
          {
            "name": "FixReversedRoadLinearLand",
            "function": "FixReversedRoadLinearLand"
          },
          {
              "name": "numberFollowingCarBrakes",
              "function": "numberBinaryBlocks",
              "binary_column": "FollowCarBrakingStatus",
              "new_column": "carBlocks",
              "only_on": 0,
              "extend_blocks": 1
          }
      ],
  
      "rois": [
          {"type": "column", "columnname": "carBlocks"}
      ],
  
      "metrics": [

        {
          "name": "throttleReactionTime",
          "function": "throttleReactionTime"
        },
        {
          "name": "maxAcceleration",
          "function": "maxAcceleration"
        },
          {
            "name": "R2DIDColumns",
            "function": "R2DIDColumns"
          },
          {
              "name": "meanVelocity",
              "function": "colMean",
              "var": "Velocity"
          },
          {
              "name": "sdVelocity",
              "function": "colSD",
              "var": "Velocity"
          },
          {
              "name": "sdLP",
              "function": "colSD",
              "var": "RoadOffset"
          },
          {
              "name": "minLP",
              "function": "colMin",
              "var": "RoadOffset"
          },
          {
              "name": "maxLP",
              "function": "colMax",
              "var": "RoadOffset"
          },
          {
              "name": "meanLP",
              "function": "colMean",
              "var": "RoadOffset"
          },
          {
                "name": "startSimTime",
                "function": "colMin",
                "var": "SimTime"
          },
        {
          "name": "startXPos",
          "function": "colMin",
          "var": "XPos"
        },
        {
          "name": "reactionTime",
          "function": "reactionBrakeFirstTrue",
          "var": "Brake"
        }, 
        {
            "name": "minHeadwayDistance",
            "function": "colMin",
            "var": "HeadwayDistance"
        }
  
      ]
   }
  