{
    "rois": [
        {
            "type": "column",
            "columnname": "TaskNum"
        }
    ],
    "filters": [
        {
            "name": "smoothGazeData",
            "function": "smoothGazeData",
            "gazeColName": "ESTIMATED_CLOSEST_WORLD_INTERSECTION"
        },
        {
            "name": "numberSwitchBlocks",
            "function": "numberSwitchBlocks"
        },
        {
            "name": "mergeEvents",
            "function": "mergeEvents",
            "eventDirectory": "event_files"
        },
        {
            "name": "mergeFintoTaskFail",
            "function": "mergeFintoTaskFail"
        },
        {
            "name": "numberTaskInstance",
            "function": "numberTaskInstance"
        },
        {
            "name": "writeToCSV",
            "function": "writeToCSV",
            "outputDirectory": "output_test"
        }
    ],
    "metrics": [
        {
            "name": "speedbumpHondaGaze2",
            "function": "speedbumpHondaGaze2"
        }
    ]
}